[
    {
        "processed_file": "image.jpg",
        "s3_storage_uri": "s3://security-employee-vault-nik/employees/image.jpg",
        "total_faces_detected": 1,
        "faces": [
            {
                "face_index": 1,
                "confidence": 100.0
            }
        ]
    },
    {
        "timestamp": "2026-07-08 10:27:57",
        "processed_file": "image.jpg",
        "s3_storage_uri": "s3://security-employee-vault-nik/employees/image.jpg",
        "total_faces_detected": 1,
        "faces": [
            {
                "face_index": 1,
                "confidence": 100.0
            }
        ]
    },
    {
        "timestamp": "2026-07-08 10:28:14",
        "processed_file": "employee_01.jpg",
        "s3_storage_uri": "s3://security-employee-vault-nik/employees/employee_01.jpg",
        "total_faces_detected": 1,
        "faces": [
            {
                "face_index": 1,
                "confidence": 100.0
            }
        ]
    },
    {
        "timestamp": "2026-07-08 10:29:31",
        "processed_file": "person2.jpg",
        "s3_storage_uri": "s3://security-employee-vault-nik/employees/person2.jpg",
        "total_faces_detected": 1,
        "faces": [
            {
                "face_index": 1,
                "confidence": 100.0
            }
        ]
    },
    {
        "timestamp": "2026-07-08 10:30:34",
        "processed_file": "1images.jpg",
        "s3_storage_uri": "s3://security-employee-vault-nik/employees/1images.jpg",
        "total_faces_detected": 1,
        "faces": [
            {
                "face_index": 1,
                "confidence": 100.0
            }
        ]
    },
    {
        "timestamp": "2026-07-08 10:37:34",
        "processed_file": "1images.jpg",
        "s3_storage_uri": "s3://security-employee-vault-nik/employees/1images.jpg",
        "total_faces_detected": 1,
        "faces": [
            {
                "face_index": 1,
                "confidence": 100.0
            }
        ]
    }
]